api4p4/__init__.py
api4p4/decorator.py
api4p4/p4.py
api4p4/p4_client.py
api4p4/type_utils.py
p4/__init__.py
p4/decorator.py
p4/p4_client.py
p4/type_utils.py
api4p4-0.18.dist-info/LICENSE
api4p4-0.18.dist-info/METADATA
api4p4-0.18.dist-info/WHEEL
api4p4-0.18.dist-info/top_level.txt
api4p4-0.18.dist-info/RECORD
